{"X0MzT3gUx+G47RtridZOTg==":"favicon-1-122x122.png","eHboda41tTi3QkAAHf5AuQ==":"mbr-1920x1280.jpg","BxcyfXpiGJ9y+s7Pk0K23Q==":"mbr-1920x1283.jpg","kIAT0+OV7rbAtkXCz24omA==":"mbr-1-1920x1280.jpg","Ml52ZxoW0jqJEYdPkRG1tA==":"mbr-1920x1195.jpg","xYt9zgsVL64gPY4Cxi2uig==":"mbr-1920x1079.jpg","6BOzyHVYKj0lUozRW3sLlQ==":"mbr-1920x1080.jpg","d5aqqoRZNx8Mo6lB6JuIIw==":"mbr-1920x1279.jpg","CkG1KXWgu43Gl/TCbX9btA==":"mbr-1-1920x1080.jpg","3qvX7FTfirXqcMqalcFMiw==":"mbr-1920x1205.jpg","FcpzLwFgOZoT/u6tb31vZQ==":"mbr-2-1920x1280.jpg","8AHUU26XGKn60y5fs/t/sA==":"mbr-1920x1106.jpg","Dwb5fypxZ+6ysLXKkoFO8Q==":"mbr-1920x1277.jpg","AVv+LHefvpsOBtIvwQTJ6A==":"mbr-1920x1277.jpg","gFTG+fUsFIe9oaKjk2TzRw==":"logo2-130x130.png","0WHfEmp93/QykGBOCw6wfw==":"background1-1920x1280.jpg","LtVgjz+o4I/QcSF/Tbj39A==":"background2-1920x1280.jpg","uXQyrYfGUMPRshOx1x2MVA==":"background1-1-1920x1280.jpg","Gb0T4WnSTNjEBnWqtIVrjg==":"background2-1-1920x1280.jpg","5n4NowbcEzUJJz3R7SRfrQ==":"background3-1920x1280.jpg","PPNWLHGPh578JiHNSUsCYg==":"background5-1920x1280.jpg","+gh7afDKbUOaSK8kBsvNqA==":"background7-1920x1280.jpg","FXmli4ph6NabdFijmXHkxw==":"mbr-1920x1280.jpg","1Wd25dvTIpsIl7Ngu4xihw==":"background6-1920x1280.jpg","9oB3p0dVwg0QZZfmqTaVWg==":"background8-1920x1280.jpg","U2vRcE1s3H1et6sN/EwABA==":"background4-1920x1280.jpg","ICjvRlp97+b0MO8cktCaDA==":"background7-1920x1280.jpeg","WG+Vv2XwrFcPK7UzTqETnQ==":"face2-1162x1743.jpg","yzhdd8Ax9bQBLwQu6wDKdg==":"1596952386373-905x1280.jpg","izvQRL8La/mPkospWCWxzA==":"1596952365150-1080x1039.png","zUfIwkALJDVYQGrKetDDbw==":"background9-1920x1280.jpg","e56cZ7CvQv5mA1bTZfVhZQ==":"background10-1920x1280.jpg","KufYOK4+TBFFQQpMjpCGLg==":"background11-1920x1280.jpg","GlSG2D3mbT6B/4BWXbP6Hg==":"background12-1920x1280.jpg"}